stateless/__init__.py
stateless/main.py
stateless/cli/__init__.py
stateless/cli/routes.py
stateless/cli/utils.py
stateless/cli/commands/__init__.py
stateless/cli/commands/api_keys.py
stateless/cli/commands/buckets.py
stateless/cli/commands/chains.py
stateless/cli/commands/entrypoints.py
stateless/cli/commands/offerings.py
stateless/cli/commands/providers.py
stateless/cli/commands/regions.py
stateless/cli/commands/users.py
stateless/cli/models/__init__.py
stateless/cli/models/accounts.py
stateless/cli/models/api_keys.py
stateless/cli/models/billing.py
stateless/cli/models/buckets.py
stateless/cli/models/chains.py
stateless/cli/models/entrypoints.py
stateless/cli/models/offerings.py
stateless/cli/models/providers.py
stateless/cli/models/regions.py
stateless/cli/models/users.py
stateless/eth/__init__.py
stateless/eth/provider.py
stateless_sdk-0.0.22.dist-info/LICENSE
stateless_sdk-0.0.22.dist-info/METADATA
stateless_sdk-0.0.22.dist-info/WHEEL
stateless_sdk-0.0.22.dist-info/entry_points.txt
stateless_sdk-0.0.22.dist-info/top_level.txt
stateless_sdk-0.0.22.dist-info/RECORD
