Metadata-Version: 2.1
Name: stateless-sdk
Version: 0.0.22
Summary: A CLI for interacting with the Stateless Gateway
Author-email: blockjoe <joe@stateless.solutions>
Requires-Python: >=3.10
License-File: LICENSE
Requires-Dist: typer ~=0.9.0
Requires-Dist: pydantic ~=2.4.2
Requires-Dist: httpx ~=0.24.1
Requires-Dist: rich ~=13.6.0
Requires-Dist: ujson ~=5.8.0
Requires-Dist: inquirer ~=3.1.4
Provides-Extra: dev
Requires-Dist: black >=23.7.0 ; extra == 'dev'
Requires-Dist: flake8 ; extra == 'dev'
Requires-Dist: isort ; extra == 'dev'
Provides-Extra: testing
Requires-Dist: pytest ; extra == 'testing'
Requires-Dist: pytest-asyncio ; extra == 'testing'
Requires-Dist: pytest-dotenv ; extra == 'testing'
Requires-Dist: pytest-httpx ; extra == 'testing'
Requires-Dist: pytest-cov ; extra == 'testing'
Requires-Dist: respx ; extra == 'testing'
